{"nodes": [{"id": "d_github_repos_kidos_main_web_components_askanything_tsx", "label": "AskAnything.tsx", "file_type": "code", "source_file": "D:\\Github Repos\\KidOS-main\\web\\components\\AskAnything.tsx", "source_location": "L1"}, {"id": "askanything_askanything", "label": "AskAnything()", "file_type": "code", "source_file": "D:\\Github Repos\\KidOS-main\\web\\components\\AskAnything.tsx", "source_location": "L6"}], "edges": [{"source": "d_github_repos_kidos_main_web_components_askanything_tsx", "target": "react", "relation": "imports_from", "confidence": "EXTRACTED", "source_file": "D:\\Github Repos\\KidOS-main\\web\\components\\AskAnything.tsx", "source_location": "L3", "weight": 1.0}, {"source": "d_github_repos_kidos_main_web_components_askanything_tsx", "target": "card", "relation": "imports_from", "confidence": "EXTRACTED", "source_file": "D:\\Github Repos\\KidOS-main\\web\\components\\AskAnything.tsx", "source_location": "L4", "weight": 1.0}, {"source": "d_github_repos_kidos_main_web_components_askanything_tsx", "target": "askanything_askanything", "relation": "contains", "confidence": "EXTRACTED", "source_file": "D:\\Github Repos\\KidOS-main\\web\\components\\AskAnything.tsx", "source_location": "L6", "weight": 1.0}], "raw_calls": [{"caller_nid": "askanything_askanything", "callee": "useState", "source_file": "D:\\Github Repos\\KidOS-main\\web\\components\\AskAnything.tsx", "source_location": "L7"}, {"caller_nid": "askanything_askanything", "callee": "useState", "source_file": "D:\\Github Repos\\KidOS-main\\web\\components\\AskAnything.tsx", "source_location": "L8"}, {"caller_nid": "askanything_askanything", "callee": "useState", "source_file": "D:\\Github Repos\\KidOS-main\\web\\components\\AskAnything.tsx", "source_location": "L9"}, {"caller_nid": "askanything_askanything", "callee": "(\n    <Card color=\"purple\" className=\"flex flex-col h-[500px] animate-pop-in\">\n      <div className=\"flex-1 overflow-y-auto mb-4 space-y-4 pr-2\">\n        {messages.length === 0 ? (\n          <div className=\"h-full flex flex-col items-center justify-center text-center text-gray-400\">\n            <span className=\"text-5xl mb-3 opacity-50\">\u2728</span>\n            <p className=\"font-bold text-gray-500\">Try asking: &quot;Why is the sky blue?&quot;</p>\n            <p className=\"text-sm\">or &quot;How do airplanes fly?&quot;</p>\n          </div>\n        ) : (\n          messages.map((m, i) => (\n            <div key={i} className={`flex ${m.role === 'user' ? 'justify-end' : 'justify-start'}`}>\n              <div\n                className={`max-w-[80%] rounded-2xl px-5 py-3 text-sm font-bold shadow-sm ${\n                  m.role === 'user'\n                    ? 'bg-kidos-purple text-white rounded-br-none'\n                    : 'bg-white text-gray-700 border border-gray-100 rounded-bl-none'\n                }`}\n              >\n                {m.text}\n              </div>\n            </div>\n          ))\n        )}\n        {loading && (\n          <div className=\"flex justify-start\">\n            <div className=\"bg-white text-gray-700 border border-gray-100 rounded-2xl rounded-bl-none px-5 py-3 text-sm font-bold flex items-center gap-2\">\n              <span className=\"animate-bounce\">\ud83e\udd16</span> Thinking...\n            </div>\n          </div>\n        )}\n      </div>\n\n      <form onSubmit={handleAsk} className=\"relative mt-auto\">\n        <div className=\"flex gap-2\">\n          <div className=\"relative flex-1\">\n            <input\n              type=\"text\"\n              value={query}\n              onChange={(e) => setQuery(e.target.value)}\n              placeholder=\"Ask a question...\"\n              className=\"w-full bg-white border border-gray-200 rounded-full py-4 pl-6 pr-12 font-bold text-gray-700 focus:outline-none focus:border-kidos-purple focus:ring-2 focus:ring-purple-100 transition-all shadow-inner\"\n              disabled={loading}\n            />\n            <button\n              type=\"button\"\n              className=\"absolute right-4 top-1/2 -translate-y-1/2 text-gray-400 hover:text-kidos-purple transition-colors text-xl\"\n              title=\"Voice Input\"\n            >\n              \ud83c\udfa4\n            </button>\n          </div>\n          <button\n            type=\"submit\"\n            disabled={!query.trim() || loading}\n            className=\"w-14 h-14 bg-kidos-purple rounded-full flex items-center justify-center text-white text-xl hover:scale-105 transition-transform disabled:opacity-50 disabled:hover:scale-100 shrink-0 shadow-sm\"\n          >\n            \u2728\n          </button>\n        </div>\n        \n        {/* Action Buttons */}\n        <div className=\"flex gap-2 mt-4 overflow-x-auto pb-1 no-scrollbar\">\n          <button type=\"button\" onClick={() => setQuery('Explain black holes')} className=\"bg-white border border-gray-200 text-gray-600 px-4 py-2 rounded-full text-sm font-bold hover:bg-gray-50 whitespace-nowrap shadow-sm\">\ud83d\udd0d Explain more</button>\n          <button type=\"button\" onClick={() => setQuery('Tell a story about a brave dog')} className=\"bg-white border border-gray-200 text-gray-600 px-4 py-2 rounded-full text-sm font-bold hover:bg-gray-50 whitespace-nowrap shadow-sm\">\ud83d\udcd6 Tell a story</button>\n          <button type=\"button\" onClick={()", "source_file": "D:\\Github Repos\\KidOS-main\\web\\components\\AskAnything.tsx", "source_location": "L45"}, {"caller_nid": "askanything_askanything", "callee": "map", "source_file": "D:\\Github Repos\\KidOS-main\\web\\components\\AskAnything.tsx", "source_location": "L55"}, {"caller_nid": "askanything_askanything", "callee": "(\n          <div className=\"flex justify-start\">\n            <div className=\"bg-white text-gray-700 border border-gray-100 rounded-2xl rounded-bl-none px-5 py-3 text-sm font-bold flex items-center gap-2\">\n              <span className=\"animate-bounce\">\ud83e\udd16</span> Thinking...\n            </div>\n          </div>\n        )}\n      </div>\n\n      <form onSubmit={handleAsk} className=\"relative mt-auto\">\n        <div className=\"flex gap-2\">\n          <div className=\"relative flex-1\">\n            <input\n              type=\"text\"\n              value={query}\n              onChange={(e) => setQuery(e.target.value)}\n              placeholder=\"Ask a question...\"\n              className=\"w-full bg-white border border-gray-200 rounded-full py-4 pl-6 pr-12 font-bold text-gray-700 focus:outline-none focus:border-kidos-purple focus:ring-2 focus:ring-purple-100 transition-all shadow-inner\"\n              disabled={loading}\n            />\n            <button\n              type=\"button\"\n              className=\"absolute right-4 top-1/2 -translate-y-1/2 text-gray-400 hover:text-kidos-purple transition-colors text-xl\"\n              title=\"Voice Input\"\n            >\n              \ud83c\udfa4\n            </button>\n          </div>\n          <button\n            type=\"submit\"\n            disabled={!query.trim() || loading}\n            className=\"w-14 h-14 bg-kidos-purple rounded-full flex items-center justify-center text-white text-xl hover:scale-105 transition-transform disabled:opacity-50 disabled:hover:scale-100 shrink-0 shadow-sm\"\n          >\n            \u2728\n          </button>\n        </div>\n        \n        {/* Action Buttons */}\n        <div className=\"flex gap-2 mt-4 overflow-x-auto pb-1 no-scrollbar\">\n          <button type=\"button\" onClick={() => setQuery('Explain black holes')} className=\"bg-white border border-gray-200 text-gray-600 px-4 py-2 rounded-full text-sm font-bold hover:bg-gray-50 whitespace-nowrap shadow-sm\">\ud83d\udd0d Explain more</button>\n          <button type=\"button\" onClick={()", "source_file": "D:\\Github Repos\\KidOS-main\\web\\components\\AskAnything.tsx", "source_location": "L69"}, {"caller_nid": "askanything_askanything", "callee": "trim", "source_file": "D:\\Github Repos\\KidOS-main\\web\\components\\AskAnything.tsx", "source_location": "L99"}]}